MANIFEST.in
setup.cfg
setup.py
docs/LICENSE
docs/README.rst
lib/commit_entropy/__init__.py
lib/commit_entropy/app.py
lib/commit_entropy/settings.py
lib/commit_entropy.egg-info/PKG-INFO
lib/commit_entropy.egg-info/SOURCES.txt
lib/commit_entropy.egg-info/dependency_links.txt
lib/commit_entropy.egg-info/entry_points.txt
lib/commit_entropy.egg-info/requires.txt
lib/commit_entropy.egg-info/top_level.txt
lib/commit_entropy/commands/__init__.py
lib/commit_entropy/commands/csv_printer.py
lib/commit_entropy/parser/__init__.py
lib/commit_entropy/parser/git_log_parser.py