Metadata-Version: 1.0
Name: commit-entropy
Version: 0.2.0
Summary: UNKNOWN
Home-page: UNKNOWN
Author: Grip QA
Author-email: UNKNOWN
License: apache
Platform: any
